decoder_fsm.v
`timescale 1ns/1ps
module decoder_fsm #(
    parameter MAX_CODE = 9  // maximum Huffman code length
)(
    input  wire        clk,
    input  wire        reset,

    // Handshake with input
    input  wire        svalid,    // input data valid
    input  wire [3:0]  in_data,   // input bits (LSB = newest)
    input  wire [2:0]  in_len,    // number of valid bits (1–4)
    output reg         aready,    // request more input bits

    // Interface to shift register
    output reg         load_bits, // tell shifter to append bits
    output reg         shift_en,  // shift out matched bits
    output reg  [3:0]  shift_len, // number of bits to shift
    input  wire [MAX_CODE-1:0] shift_buf,
    input  wire [3:0]  bit_count, // valid bits in buffer

    // Output side
    output reg  signed [3:0] decodedData,
    output reg         tvalid      // decodedData valid
);

    //--------------------------------------------------------
    // Internal signals for match detection
    //--------------------------------------------------------
    reg        match_flag_reg;
    reg        match_flag_comb;

    reg  signed [3:0] match_symbol_comb;
    reg  [3:0]        match_len_comb;

    reg  signed [3:0] match_symbol_reg;
    reg  [3:0]        match_len_reg;

    //--------------------------------------------------------
    // Combinational match detection (bit-count aware lookup, LSB-first)
    //--------------------------------------------------------
    always @(*) begin
        match_flag_comb   = 1'b0;
        match_symbol_comb = 4'd0;
        match_len_comb    = 4'd0;

        // 1-bit code (need at least 1 bit)
        if (bit_count >= 1 && shift_buf[0] == 1'b0) begin
            match_flag_comb   = 1'b1;
            match_symbol_comb = 4'sd0;
            match_len_comb    = 4'd1;
        end

        // 3-bit codes (need at least 3 bits)
        else if (bit_count >= 3 && shift_buf[0 +: 3] == 3'b001) begin
            match_flag_comb   = 1'b1;
            match_symbol_comb = 4'sd1;
            match_len_comb    = 4'd3;
        end
// 4-bit codes (need at least 4 bits)
else if (bit_count >= 4) begin
    case (shift_buf[0 +: 4])
        4'b0101: begin
            match_flag_comb   = 1'b1;
            match_symbol_comb = -4'sd3;
            match_len_comb    = 4'd4;
        end
        4'b0011: begin
            match_flag_comb   = 1'b1;
            match_symbol_comb =  4'sd2;
            match_len_comb    = 4'd4;
        end
        4'b1011: begin
            match_flag_comb   = 1'b1;
            match_symbol_comb = -4'sd2;
            match_len_comb    = 4'd4;
        end
        4'b0111: begin
            match_flag_comb   = 1'b1;
            match_symbol_comb = -4'sd1;
            match_len_comb    = 4'd4;
        end
        default: match_flag_comb = 1'b0;
    endcase
end

// 5-bit codes (need at least 5 bits)
if (!match_flag_comb && bit_count >= 5) begin
    case (shift_buf[0 +: 5])
        5'b11101: begin
            match_flag_comb   = 1'b1;
            match_symbol_comb = -4'sd4;
            match_len_comb    = 4'd5;
        end
        5'b01111: begin
            match_flag_comb   = 1'b1;
            match_symbol_comb =  4'sd3;
            match_len_comb    = 4'd5;
        end
        default: match_flag_comb = 1'b0;
    endcase
end

// 6-bit codes (need at least 6 bits)
if (!match_flag_comb && bit_count >= 6) begin
    case (shift_buf[0 +: 6])
        6'b101101: begin
            match_flag_comb   = 1'b1;
            match_symbol_comb = -4'sd5;
            match_len_comb    = 4'd6;
        end
        6'b111111: begin
            match_flag_comb   = 1'b1;
            match_symbol_comb =  4'sd4;
            match_len_comb    = 4'd6;
        end
        default: match_flag_comb = 1'b0;
    endcase
end

// 7-bit codes (need at least 7 bits)
if (!match_flag_comb && bit_count >= 7) begin
    case (shift_buf[0 +: 7])
        7'b0001101: begin
            match_flag_comb   = 1'b1;
            match_symbol_comb = -4'sd6;
            match_len_comb    = 4'd7;
        end
        7'b1001101: begin
            match_flag_comb   = 1'b1;
            match_symbol_comb =  4'sd6;
            match_len_comb    = 4'd7;
        end
        7'b1011111: begin
            match_flag_comb   = 1'b1;
            match_symbol_comb =  4'sd5;
            match_len_comb    = 4'd7;
        end
        default: match_flag_comb = 1'b0;
    endcase
end

// 8-bit codes (need at least 8 bits)
if (!match_flag_comb && bit_count >= 8) begin
    if (shift_buf[0 +: 8] == 8'b00011111) begin
        match_flag_comb   = 1'b1;
        match_symbol_comb = -4'sd7;
        match_len_comb    = 4'd8;
    end
end

// 9-bit codes (need at least 9 bits)
if (!match_flag_comb && bit_count >= 9) begin
    case (shift_buf[0 +: 9])
        9'b010011111: begin
            match_flag_comb   = 1'b1;
            match_symbol_comb = -4'sd8;
            match_len_comb    = 4'd9;
        end
        9'b110011111: begin
            match_flag_comb   = 1'b1;
            match_symbol_comb =  4'sd7;
            match_len_comb    = 4'd9;
        end
        default: match_flag_comb = 1'b0;
    endcase
end

    end

    //--------------------------------------------------------
    // State Declaration
    //--------------------------------------------------------
    localparam [2:0]
        S_IDLE   = 3'd0,
        S_LOAD   = 3'd1,
        S_DECODE = 3'd2,
        S_SHIFT  = 3'd3,
        S_OUTPUT = 3'd4;

    reg [2:0] state, next_state;

    //--------------------------------------------------------
    // Sequential register for match_flag/symbol/len
    //--------------------------------------------------------
    always @(posedge clk or posedge reset) begin
        if (reset) begin
            match_flag_reg   <= 1'b0;
            match_symbol_reg <= 4'd0;
            match_len_reg    <= 4'd0;
        end
        else if (state == S_OUTPUT) begin
            match_flag_reg <= 1'b0; // clear after output
        end
        else if (state == S_DECODE && match_flag_comb) begin
            match_flag_reg   <= 1'b1;
            match_symbol_reg <= match_symbol_comb;
            match_len_reg    <= match_len_comb;
        end
        else begin 
            match_flag_reg <= 1'b0; 
            match_len_reg  <= match_len_comb; 
        end
    end

    //--------------------------------------------------------
    // Sequential State Update
    //--------------------------------------------------------
    always @(posedge clk or posedge reset) begin
        if (reset)
            state <= S_IDLE;
        else
            state <= next_state;
    end

    //--------------------------------------------------------
    // Next-State Logic
    //--------------------------------------------------------
    always @(*) begin
        next_state = state;
        case (state)
            S_IDLE:   if (svalid) next_state = S_DECODE;

            S_LOAD:   next_state = S_DECODE;

            S_DECODE: begin
                if (match_flag_reg)
                    next_state = S_SHIFT;
                else if (!match_flag_reg && aready && svalid)
                    next_state = S_LOAD;
                else
                    next_state = S_DECODE;
            end

            S_SHIFT:  next_state = S_OUTPUT;
            S_OUTPUT: next_state = S_DECODE;
        endcase
    end

    //--------------------------------------------------------
    // Output / Control Logic
    //--------------------------------------------------------
    always @(posedge clk or posedge reset) begin
        if (reset) begin
            aready      <= 1'b0;
            load_bits   <= 1'b0;
            shift_en    <= 1'b0;
            shift_len   <= 4'd0;
            decodedData <= 4'd0;
            tvalid      <= 1'b0;
        end else begin
            // Defaults
            aready    <= 1'b0;
            load_bits <= 1'b0;
            shift_en  <= 1'b0;
            shift_len <= 4'd0;
            tvalid    <= 1'b0;

            case (state)
                S_IDLE:   aready <= 1'b1;

                S_LOAD:   load_bits <= 1'b1;

                S_DECODE: begin 
                    aready <= (bit_count < MAX_CODE);
                end

                S_SHIFT: begin
                    shift_en  <= match_flag_reg;
                    shift_len <= match_len_reg;   // use latched length
                end

                S_OUTPUT: begin
                    decodedData <= match_symbol_reg;
                    tvalid      <= 1'b1;
                end
            endcase
        end
    end

endmodule

shift_reg.v
//============================================================
// shift_reg.v — Top-level with internal FSM instantiation
//============================================================
`timescale 1ns/1ps
module shift_reg #(
    parameter MAX_CODE = 9,
    parameter MIN_SAFE_BITS = 3
)(
    input  wire             clk,
    input  wire             reset,
    input  wire [3:0]       in_bits,
    input  wire [2:0]       in_len,
    input  wire             sValid,
    // Final decoded outputs
    output reg  signed [3:0] decodedData,
    output wire             tvalid
    //output reg               buffer_ready
);
    //--------------------------------------------------------
    // Internal signals
    //--------------------------------------------------------
    reg  [MAX_CODE-1:0] shift_buf;
    reg  [3:0]          bit_count;
    wire                load_bits;
    wire                shift_en;
    wire [3:0]          shift_len;
    wire                aready;

    // internal handshake and match info
    wire match_flag;
    wire signed [3:0] match_symbol;
    wire [3:0] match_len;
    wire fsm_tvalid; 
    wire fsm_svalid;

    assign fsm_svalid = sValid;
    // Define a wire for reversed bits
    wire [MAX_CODE-1:0] in_bits_reversed;

// Function to reverse lower `len` bits of `data`
function automatic [MAX_CODE-1:0] reverse_bits;
    input [MAX_CODE-1:0] data;
    input [3:0] len;  // or appropriate width for your in_len
    integer i;
    begin
        reverse_bits = {MAX_CODE{1'b0}};  // default all zeros
        for (i = 0; i < len; i = i + 1)
            reverse_bits[i] = data[len - 1 - i];
    end
endfunction
assign in_bits_reversed = reverse_bits(in_bits, in_len);

    //--------------------------------------------------------
    // FSM Instantiation
    //--------------------------------------------------------
    decoder_fsm #(
        .MAX_CODE(MAX_CODE)
    ) u_fsm (
        .clk(clk),
        .reset(reset),
        .svalid(fsm_svalid),
        .in_data(in_bits),
        .in_len(in_len),
        .aready(aready),
        .load_bits(load_bits),
        .shift_en(shift_en),
        .shift_len(shift_len),
        .shift_buf(shift_buf),
        .bit_count(bit_count),
        .decodedData(match_symbol),
        .tvalid(fsm_tvalid)
    );

    //--------------------------------------------------------
    // Valid Window (Aligned Bit View)
    //--------------------------------------------------------
    reg [MAX_CODE-1:0] valid_window;

    always @(*) begin
        // Generate the left-aligned valid bits view (no false zeros)
        valid_window = shift_buf << (MAX_CODE - bit_count);
    end

    //--------------------------------------------------------
    // Shift Register Logic
    //--------------------------------------------------------
    integer i;
    assign tvalid = fsm_tvalid;

    // Mask to keep only 'in_len' valid bits
    reg [MAX_CODE-1:0] in_masked;

    // ==========================================================
    // Barrel-shift style bit buffer (Quartus-safe Verilog-2001)
    // ==========================================================
   always @(posedge clk or posedge reset) begin
    if (reset) begin
        shift_buf   <= {MAX_CODE{1'b0}};
        bit_count   <= 0;
        decodedData <= 0;
    end else begin
        // -----------------------------
        // Load or append new bits
        // -----------------------------
        if (load_bits && (bit_count + in_len <= MAX_CODE) && (in_len != 0)) begin
            if (bit_count == 0) begin
                // Buffer empty → load reversed input at LSB side
                shift_buf <= in_bits_reversed;
            end else begin
                // Buffer has bits → append reversed input after existing valid bits
                shift_buf <= (shift_buf) | (in_bits_reversed << bit_count);
            end
            bit_count <= bit_count + in_len;
        end

        // -----------------------------
        // Shift bits out (LSB side)
        // -----------------------------
        else if (shift_en && (bit_count >= shift_len) && (shift_len != 0)) begin
            shift_buf <= shift_buf >> shift_len;
            bit_count <= bit_count - shift_len;
        end

        // -----------------------------
        // FSM decoded output latch
        // -----------------------------
        if (tvalid)
            decodedData <= match_symbol;
    end
end
endmodule

tb_shift_reg.v
`timescale 1ns/1ps

module tb_shift_reg;
    parameter MAX_CODE = 9;

    reg clk, reset;
    reg sValid;
    reg [3:0] in_bits;
    reg [2:0] in_len;

    wire signed [3:0] decodedData;
    wire tvalid;
	 // 256-bit encoded string
    reg [255:0] encoded_bits;

    // Internal debug
    wire [MAX_CODE-1:0] shift_buf = uut.shift_buf;
    wire [3:0] bit_count           = uut.bit_count;
    wire shift_en_tb               = uut.u_fsm.shift_en;
    // Counter for decoded codewords
    integer codeword_count;
	 integer i;
    reg [3:0] chunk;
    reg [2:0] chunk_len;
    // Instantiate DUT
    shift_reg #(.MAX_CODE(MAX_CODE)) uut (
        .clk(clk),
        .reset(reset),
        .sValid(sValid),
        .in_bits(in_bits),
        .in_len(in_len),
        .decodedData(decodedData),
        .tvalid(tvalid)
    );

    // Clock generation
    always #5 clk = ~clk;

    // Display
    initial begin
        $display("Time(ns) | clk↑ | sValid | shift_en | in_bits | in_len | bit_count | shift_buf | tvalid | decodedData");
        forever begin
            @(posedge clk);
            $display("%8t |   ↑   |   %b    |    %b     |  %04b  |   %0d   |    %0d    | %09b |   %b   |   %0d",
                     $time, sValid, shift_en_tb, in_bits, in_len, bit_count, shift_buf, tvalid, decodedData);
        end
    end

    // Task to send a chunk
    task send_chunk(input [3:0] bits, input [2:0] len);
    begin
        in_bits = bits;
        in_len  = len;
        @(posedge clk);
        sValid = 1;
        repeat(2)@(posedge clk);
        sValid = 0;
        repeat (16) @(posedge clk);  // idle a few cycles
    end
    endtask

    initial codeword_count = 0;

    // Increment counter on tvalid
    always @(posedge clk) begin
        if (tvalid)
            codeword_count = codeword_count + 1;
    end

    // === Send 256-bit encoded string as 4-bit chunks ===
    initial begin
        clk = 0;
        reset = 1;
        sValid = 0;
        in_bits = 0;
        in_len = 0;
        codeword_count = 0;

        #20 reset = 0;

        
        encoded_bits = 256'b0001100101101001110001100110000100001101110000011110011101110100100100100011100110100000110000110100000001000011101110110111100110111001011100000111001100001010110100000011100110111100010011100100100000000101011011001101111011110111011001101111011010110000;

       

        i = 255; // start from MSB
        while (i >= 0) begin
            if (i >= 3) chunk_len = 3'd4;
            else         chunk_len = i + 1;

            case (chunk_len)
                3'd4: chunk = encoded_bits[i -: 4];
                3'd3: chunk = encoded_bits[i -: 3];
                3'd2: chunk = encoded_bits[i -: 2];
                3'd1: chunk = encoded_bits[i -: 1];
                default: chunk = 0;
            endcase

            send_chunk(chunk, chunk_len);
            i = i - chunk_len;
        end

        // Wait a few cycles to finish decoding
        repeat (50) @(posedge clk);

        $display("=== 256-bit encoded string simulation done ===");
        $display("Total codewords decoded: %0d", codeword_count);

        $finish;
    end
endmodule

tb_shift_reg.vcd
$date
	Thu Nov 13 15:37:55 2025
$end
$version
	Questa Intel Starter FPGA Edition Version 2024.3
$end
$timescale
	1ps
$end

$scope module tb_shift_reg $end
$var parameter 32 ! MAX_CODE $end
$var reg 1 " clk $end
$var reg 1 # reset $end
$var reg 1 $ sValid $end
$var reg 4 % in_bits [3:0] $end
$var reg 3 & in_len [2:0] $end
$var wire 1 ' decodedData [3] $end
$var wire 1 ( decodedData [2] $end
$var wire 1 ) decodedData [1] $end
$var wire 1 * decodedData [0] $end
$var wire 1 + tvalid $end
$var reg 256 , encoded_bits [255:0] $end
$var wire 1 - shift_buf [8] $end
$var wire 1 . shift_buf [7] $end
$var wire 1 / shift_buf [6] $end
$var wire 1 0 shift_buf [5] $end
$var wire 1 1 shift_buf [4] $end
$var wire 1 2 shift_buf [3] $end
$var wire 1 3 shift_buf [2] $end
$var wire 1 4 shift_buf [1] $end
$var wire 1 5 shift_buf [0] $end
$var wire 1 6 bit_count [3] $end
$var wire 1 7 bit_count [2] $end
$var wire 1 8 bit_count [1] $end
$var wire 1 9 bit_count [0] $end
$var wire 1 : shift_en_tb $end
$var integer 32 ; codeword_count $end
$var integer 32 < i $end
$var reg 4 = chunk [3:0] $end
$var reg 3 > chunk_len [2:0] $end

$scope task send_chunk $end
$var reg 4 ? bits [3:0] $end
$var reg 3 @ len [2:0] $end
$upscope $end

$scope module uut $end
$var parameter 32 A MAX_CODE $end
$var parameter 32 B MIN_SAFE_BITS $end
$var wire 1 C clk $end
$var wire 1 D reset $end
$var wire 1 E in_bits [3] $end
$var wire 1 F in_bits [2] $end
$var wire 1 G in_bits [1] $end
$var wire 1 H in_bits [0] $end
$var wire 1 I in_len [2] $end
$var wire 1 J in_len [1] $end
$var wire 1 K in_len [0] $end
$var wire 1 L sValid $end
$var reg 4 M decodedData [3:0] $end
$var wire 1 + tvalid $end
$var reg 9 N shift_buf [8:0] $end
$var reg 4 O bit_count [3:0] $end
$var wire 1 P load_bits $end
$var wire 1 Q shift_en $end
$var wire 1 R shift_len [3] $end
$var wire 1 S shift_len [2] $end
$var wire 1 T shift_len [1] $end
$var wire 1 U shift_len [0] $end
$var wire 1 V aready $end
$var wire 1 W match_flag $end
$var wire 1 X match_symbol [3] $end
$var wire 1 Y match_symbol [2] $end
$var wire 1 Z match_symbol [1] $end
$var wire 1 [ match_symbol [0] $end
$var wire 1 \ match_len [3] $end
$var wire 1 ] match_len [2] $end
$var wire 1 ^ match_len [1] $end
$var wire 1 _ match_len [0] $end
$var wire 1 ` fsm_tvalid $end
$var wire 1 a fsm_svalid $end
$var wire 1 b in_bits_reversed [8] $end
$var wire 1 c in_bits_reversed [7] $end
$var wire 1 d in_bits_reversed [6] $end
$var wire 1 e in_bits_reversed [5] $end
$var wire 1 f in_bits_reversed [4] $end
$var wire 1 g in_bits_reversed [3] $end
$var wire 1 h in_bits_reversed [2] $end
$var wire 1 i in_bits_reversed [1] $end
$var wire 1 j in_bits_reversed [0] $end
$var reg 9 k valid_window [8:0] $end
$var integer 32 l i $end
$var reg 9 m in_masked [8:0] $end

$scope function reverse_bits $end
$upscope $end

$scope module u_fsm $end
$var parameter 32 n MAX_CODE $end
$var parameter 3 o S_IDLE $end
$var parameter 3 p S_LOAD $end
$var parameter 3 q S_DECODE $end
$var parameter 3 r S_SHIFT $end
$var parameter 3 s S_OUTPUT $end
$var wire 1 C clk $end
$var wire 1 D reset $end
$var wire 1 a svalid $end
$var wire 1 E in_data [3] $end
$var wire 1 F in_data [2] $end
$var wire 1 G in_data [1] $end
$var wire 1 H in_data [0] $end
$var wire 1 I in_len [2] $end
$var wire 1 J in_len [1] $end
$var wire 1 K in_len [0] $end
$var reg 1 t aready $end
$var reg 1 u load_bits $end
$var reg 1 v shift_en $end
$var reg 4 w shift_len [3:0] $end
$var wire 1 x shift_buf [8] $end
$var wire 1 y shift_buf [7] $end
$var wire 1 z shift_buf [6] $end
$var wire 1 { shift_buf [5] $end
$var wire 1 | shift_buf [4] $end
$var wire 1 } shift_buf [3] $end
$var wire 1 ~ shift_buf [2] $end
$var wire 1 !! shift_buf [1] $end
$var wire 1 "! shift_buf [0] $end
$var wire 1 #! bit_count [3] $end
$var wire 1 $! bit_count [2] $end
$var wire 1 %! bit_count [1] $end
$var wire 1 &! bit_count [0] $end
$var reg 4 '! decodedData [3:0] $end
$var reg 1 (! tvalid $end
$var reg 1 )! match_flag_reg $end
$var reg 1 *! match_flag_comb $end
$var reg 4 +! match_symbol_comb [3:0] $end
$var reg 4 ,! match_len_comb [3:0] $end
$var reg 4 -! match_symbol_reg [3:0] $end
$var reg 4 .! match_len_reg [3:0] $end
$var reg 3 /! state [2:0] $end
$var reg 3 0! next_state [2:0] $end
$upscope $end
$upscope $end
$upscope $end
$enddefinitions $end
#0
$dumpvars
0"
1#
0$
b0 %
b0 &
bx ,
bx =
bx >
b0 M
b0 N
b0 O
0t
0u
0v
b0 w
b0 '!
0(!
0)!
0*!
b0 +!
b0 ,!
b0 -!
b0 .!
b0 /!
b0 0!
b0 k
bx m
bx ?
bx @
b1001 !
b1001 A
b11 B
b1001 n
b0 o
b1 p
b10 q
b11 r
b100 s
b0 ;
bx <
bx l
0*
0)
0(
0'
0+
05
04
03
02
01
00
0/
0.
0-
09
08
07
06
0:
0P
0Q
0U
0T
0S
0R
0V
zW
0[
0Z
0Y
0X
z_
z^
z]
z\
0`
0a
0j
0i
0h
0g
0f
0e
0d
0c
0b
0L
0K
0J
0I
0H
0G
0F
0E
1D
0C
0&!
0%!
0$!
0#!
0"!
0!!
0~
0}
0|
0{
0z
0y
0x
$end
#5000
1"
1C
#10000
0"
0C
#15000
1"
1C
#20000
0#
b1100101101001110001100110000100001101110000011110011101110100100100100011100110100000110000110100000001000011101110110111100110111001011100000111001100001010110100000011100110111100010011100100100000000101011011001101111011110111011001101111011010110000 ,
b11111111 <
b100 >
b1 =
b1 ?
b100 @
b1 %
b100 &
0"
1I
1H
1g
0D
0C
#25000
1"
1C
1$
1L
1a
b10 0!
1t
1V
b0 0!
b10 0!
#30000
0"
0C
#35000
1"
1C
0t
1t
b10 /!
b1 0!
#40000
0"
0C
#45000
1"
1C
0$
0L
0a
b10 0!
b1 /!
0t
1t
b1 0!
b10 0!
#50000
0"
0C
#55000
1"
1C
0t
1u
b10 /!
0V
1P
#60000
0"
0C
#65000
1"
1C
b1000 N
b100 O
0u
1t
17
12
0P
1V
1$!
1}
1*!
b1 ,!
b100000000 k
#70000
0"
0C
#75000
1"
1C
1)!
b1 .!
0t
1t
b11 0!
#80000
0"
0C
#85000
1"
1C
b11 /!
0t
1t
b100 0!
#90000
0"
0C
#95000
1"
1C
0)!
b100 /!
0t
1v
b1 w
0V
1:
1Q
1U
b10 0!
#100000
0"
0C
#105000
1"
1C
b100 N
b11 O
b10 /!
0v
b0 w
1(!
0:
0Q
0U
19
18
07
13
02
1`
1+
1&!
1%!
0$!
1~
0}
0*!
b0 ,!
1*!
b1 ,!
#110000
0"
0C
#115000
1"
1C
b1 ;
1)!
0(!
1t
0`
1V
0+
b11 0!
#120000
0"
0C
#125000
1"
1C
b11 /!
0t
1t
b100 0!
#130000
0"
0C
#135000
1"
1C
0)!
b100 /!
0t
1v
b1 w
0V
1:
1Q
1U
b10 0!
#140000
0"
0C
#145000
1"
1C
b10 N
b10 O
b10 /!
0v
b0 w
1(!
0:
0Q
0U
09
14
03
1`
1+
0&!
1!!
0~
0*!
b0 ,!
1*!
b1 ,!
#150000
0"
0C
#155000
1"
1C
b10 ;
1)!
0(!
1t
0`
1V
0+
b11 0!
#160000
0"
0C
#165000
1"
1C
b11 /!
0t
1t
b100 0!
#170000
0"
0C
#175000
1"
1C
0)!
b100 /!
0t
1v
b1 w
0V
1:
1Q
1U
b10 0!
#180000
0"
0C
#185000
1"
1C
b1 N
b1 O
b10 /!
0v
b0 w
1(!
0:
0Q
0U
19
08
15
04
1`
1+
1&!
0%!
1"!
0!!
0*!
b0 ,!
#190000
0"
0C
#195000
1"
1C
b11 ;
b0 .!
0(!
1t
0`
1V
0+
#200000
0"
0C
#205000
1"
1C
b11111011 <
b1001 =
b1001 ?
b1001 %
1E
1j
0t
1t
#210000
0"
0C
#215000
1"
1C
1$
1L
1a
b1 0!
0t
1t
b10 0!
b1 0!
#220000
0"
0C
#225000
1"
1C
0t
1t
b1 /!
b10 0!
#230000
0"
0C
#235000
1"
1C
0$
0L
0a
b1 0!
b10 0!
b10 /!
0t
1u
0V
1P
#240000
0"
0C
#245000
1"
1C
b10011 N
b101 O
0u
1t
17
14
11
0P
1V
1$!
1!!
1|
1*!
b10 +!
b100 ,!
b100110000 k
#250000
0"
0C
#255000
1"
1C
1)!
b10 -!
b100 .!
0t
1t
b11 0!
#260000
0"
0C
#265000
1"
1C
b11 /!
0t
1t
b100 0!
#270000
0"
0C
#275000
1"
1C
0)!
b100 /!
0t
1v
b100 w
0V
1:
1Q
1S
b10 0!
#280000
0"
0C
#285000
1"
1C
b1 N
b1 O
b10 /!
0v
b0 w
b10 '!
1(!
0:
0Q
1Z
0S
07
04
01
1`
1+
0$!
0!!
0|
0*!
b0 +!
b0 ,!
b100000000 k
#290000
0"
0C
#295000
1"
1C
b100 ;
b0 .!
0(!
1t
b10 M
0`
1V
1)
0+
#300000
0"
0C
#305000
1"
1C
0t
1t
#310000
0"
0C
#315000
1"
1C
0t
1t
#320000
0"
0C
#325000
1"
1C
0t
1t
#330000
0"
0C
#335000
1"
1C
0t
1t
#340000
0"
0C
#345000
1"
1C
0t
1t
#350000
0"
0C
#355000
1"
1C
0t
1t
#360000
0"
0C
#365000
1"
1C
0t
1t
#370000
0"
0C
#375000
1"
1C
0t
1t
#380000
0"
0C
#385000
1"
1C
0t
1t
#390000
0"
0C
#395000
1"
1C
b11110111 <
b110 =
b110 ?
b110 %
0H
1G
1F
0E
0j
1i
1h
0g
0t
1t
#400000
0"
0C
#405000
1"
1C
1$
1L
1a
b1 0!
0t
1t
b10 0!
b1 0!
#410000
0"
0C
#415000
1"
1C
0t
1t
b1 /!
b10 0!
#420000
0"
0C
#425000
1"
1C
0$
0L
0a
b1 0!
b10 0!
b10 /!
0t
1u
0V
1P
#430000
0"
0C
#435000
1"
1C
b1101 N
b101 O
0u
1t
17
13
12
0P
1V
1$!
1~
1}
b11010000 k
#440000
0"
0C
#445000
1"
1C
0t
1t
#450000
0"
0C
#455000
1"
1C
0t
1t
#460000
0"
0C
#465000
1"
1C
0t
1t
#470000
0"
0C
#475000
1"
1C
0t
1t
#480000
0"
0C
#485000
1"
1C
0t
1t
#490000
0"
0C
#495000
1"
1C
0t
1t
#500000
0"
0C
#505000
1"
1C
0t
1t
#510000
0"
0C
#515000
1"
1C
0t
1t
#520000
0"
0C
#525000
1"
1C
0t
1t
#530000
0"
0C
#535000
1"
1C
0t
1t
#540000
0"
0C
#545000
1"
1C
0t
1t
#550000
0"
0C
#555000
1"
1C
0t
1t
#560000
0"
0C
#565000
1"
1C
0t
1t
#570000
0"
0C
#575000
1"
1C
0t
1t
#580000
0"
0C
#585000
1"
1C
b11110011 <
b1001 =
b1001 ?
b1001 %
1H
0G
0F
1E
1j
0i
0h
1g
0t
1t
#590000
0"
0C
#595000
1"
1C
1$
1L
1a
b1 0!
0t
1t
b10 0!
b1 0!
#600000
0"
0C
#605000
1"
1C
0t
1t
b1 /!
b10 0!
#610000
0"
0C
#615000
1"
1C
0$
0L
0a
b1 0!
b10 0!
b10 /!
0t
1u
0V
1P
#620000
0"
0C
#625000
1"
1C
b100101101 N
b1001 O
0u
1t
07
16
10
1-
0P
1V
0$!
1#!
1{
1x
1*!
b1011 +!
b110 ,!
b100101101 k
#630000
0"
0C
#635000
1"
1C
1)!
b1011 -!
b110 .!
0t
0V
b11 0!
#640000
0"
0C
#645000
1"
1C
b11 /!
b100 0!
#650000
0"
0C
#655000
1"
1C
0)!
b100 /!
1v
b110 w
1:
1Q
1T
1S
b10 0!
#660000
0"
0C
#665000
1"
1C
b100 N
b11 O
b10 /!
0v
b0 w
b1011 '!
1(!
0:
0Q
1[
1X
0T
0S
18
06
05
02
00
0-
1`
1+
1%!
0#!
0"!
0}
0{
0x
0*!
b0 +!
b0 ,!
1*!
b1 ,!
b100000000 k
#670000
0"
0C
#675000
1"
1C
b101 ;
1)!
b0 -!
b1 .!
0(!
1t
b1011 M
0`
1V
1*
1'
0+
b11 0!
#680000
0"
0C
#685000
1"
1C
b11 /!
0t
1t
b100 0!
#690000
0"
0C
#695000
1"
1C
0)!
b100 /!
0t
1v
b1 w
0V
1:
1Q
1U
b10 0!
#700000
0"
0C
#705000
1"
1C
b10 N
b10 O
b10 /!
0v
b0 w
b0 '!
1(!
0:
0Q
0[
0Z
0X
0U
09
14
03
1`
1+
0&!
1!!
0~
0*!
b0 ,!
1*!
b1 ,!
#710000
0"
0C
#715000
1"
1C
b110 ;
1)!
0(!
1t
b0 M
0`
1V
0*
0)
0'
0+
b11 0!
#720000
0"
0C
#725000
1"
1C
b11 /!
0t
1t
b100 0!
#730000
0"
0C
#735000
1"
1C
0)!
b100 /!
0t
1v
b1 w
0V
1:
1Q
1U
b10 0!
#740000
0"
0C
#745000
1"
1C
b1 N
b1 O
b10 /!
0v
b0 w
1(!
0:
0Q
0U
19
08
15
04
1`
1+
1&!
0%!
1"!
0!!
0*!
b0 ,!
#750000
0"
0C
#755000
1"
1C
b111 ;
b0 .!
0(!
1t
0`
1V
0+
#760000
0"
0C
#765000
1"
1C
0t
1t
#770000
0"
0C
#775000
1"
1C
b11101111 <
b1100 =
b1100 ?
b1100 %
0H
1F
1i
0g
0t
1t
#780000
0"
0C
#785000
1"
1C
1$
1L
1a
b1 0!
0t
1t
b10 0!
b1 0!
#790000
0"
0C
#795000
1"
1C
0t
1t
b1 /!
b10 0!
#800000
0"
0C
#805000
1"
1C
0$
0L
0a
b1 0!
b10 0!
b10 /!
0t
1u
0V
1P
#810000
0"
0C
#815000
1"
1C
b111 N
b101 O
0u
1t
17
14
13
0P
1V
1$!
1!!
1~
1*!
b1111 +!
b100 ,!
b1110000 k
#820000
0"
0C
#825000
1"
1C
1)!
b1111 -!
b100 .!
0t
1t
b11 0!
#830000
0"
0C
#835000
1"
1C
b11 /!
0t
1t
b100 0!
#840000
0"
0C
#845000
1"
1C
0)!
b100 /!
0t
1v
b100 w
0V
1:
1Q
1S
b10 0!
#850000
0"
0C
#855000
1"
1C
b0 N
b1 O
b10 /!
0v
b0 w
b1111 '!
1(!
0:
0Q
1[
1Z
1Y
1X
0S
07
05
04
03
1`
1+
0$!
0"!
0!!
0~
0*!
b0 +!
b0 ,!
1*!
b1 ,!
b0 k
#860000
0"
0C
#865000
1"
1C
b1000 ;
1)!
b0 -!
b1 .!
0(!
1t
b1111 M
0`
1V
1*
1)
1(
1'
0+
b11 0!
#870000
0"
0C
#875000
1"
1C
b11 /!
0t
1t
b100 0!
#880000
0"
0C
#885000
1"
1C
0)!
b100 /!
0t
1v
b1 w
0V
1:
1Q
1U
b10 0!
#890000
0"
0C
#895000
1"
1C
b0 O
b10 /!
0v
b0 w
b0 '!
1(!
0:
0Q
0[
0Z
0Y
0X
0U
09
1`
1+
0&!
0*!
b0 ,!
#900000
0"
0C
#905000
1"
1C
b1001 ;
b0 .!
0(!
1t
b0 M
0`
1V
0*
0)
0(
0'
0+
#910000
0"
0C
#915000
1"
1C
0t
1t
#920000
0"
0C
#925000
1"
1C
0t
1t
#930000
0"
0C
#935000
1"
1C
0t
1t
#940000
0"
0C
#945000
1"
1C
0t
1t
#950000
0"
0C
#955000
1"
1C
0t
1t
#960000
0"
0C
#965000
1"
1C
b11101011 <
b110 =
b110 ?
b110 %
1G
0E
0j
1h
0t
1t
#970000
0"
0C
#975000
1"
1C
1$
1L
1a
b1 0!
0t
1t
b10 0!
b1 0!
#980000
0"
0C
#985000
1"
1C
0t
1t
b1 /!
b10 0!
#990000
0"
0C
#995000
1"
1C
0$
0L
0a
b1 0!
b10 0!
b10 /!
0t
1u
0V
1P
#1000000
0"
0C
#1005000
1"
1C
b110 N
b100 O
0u
1t
17
14
13
0P
1V
1$!
1!!
1~
1*!
b1 ,!
b11000000 k
#1010000
0"
0C
#1015000
1"
1C
1)!
b1 .!
0t
1t
b11 0!
#1020000
0"
0C
#1025000
1"
1C
b11 /!
0t
1t
b100 0!
#1030000
0"
0C
#1035000
1"
1C
0)!
b100 /!
0t
1v
b1 w
0V
1:
1Q
1U
b10 0!
#1040000
0"
0C
#1045000
1"
1C
b11 N
b11 O
b10 /!
0v
b0 w
1(!
0:
0Q
0U
19
18
07
15
03
1`
1+
1&!
1%!
0$!
1"!
0~
0*!
b0 ,!
#1050000
0"
0C
#1055000
1"
1C
b1010 ;
b0 .!
0(!
1t
0`
1V
0+
#1060000
0"
0C
#1065000
1"
1C
0t
1t
#1070000
0"
0C
#1075000
1"
1C
0t
1t
#1080000
0"
0C
#1085000
1"
1C
0t
1t
